certbot_dns_infoblox/__init__.py
certbot_dns_infoblox/dns_infoblox.py
certbot_dns_infoblox_2-0.2.4.dist-info/LICENSE.txt
certbot_dns_infoblox_2-0.2.4.dist-info/METADATA
certbot_dns_infoblox_2-0.2.4.dist-info/WHEEL
certbot_dns_infoblox_2-0.2.4.dist-info/entry_points.txt
certbot_dns_infoblox_2-0.2.4.dist-info/top_level.txt
certbot_dns_infoblox_2-0.2.4.dist-info/RECORD
